{
  "baseline_type": "TFL",
  "round_metrics": [
    {
      "round": 1,
      "aggregated_metrics": {
        "mean_train_loss": 1.381880541072499,
        "max_train_loss": 1.4307104085552718,
        "mean_train_accuracy": 0.546483344414158,
        "max_train_accuracy": 0.5568458578941795,
        "mean_training_time": 8.690642237663269,
        "max_training_time": 9.338505506515503,
        "mean_cpu_usage_mean": 6.525,
        "max_cpu_usage_mean": 6.800000000000001,
        "mean_memory_usage_max": 58.55,
        "max_memory_usage_max": 58.6,
        "mean_bandwidth_usage_mean": 0.0053554892539978026,
        "max_bandwidth_usage_mean": 0.005550265312194824
      },
      "client_metrics": {
        "6c5962e51b854d7cb972712fe5bd2d81": {
          "memory_usage_max": 58.6,
          "gpu_memory_max": 24.958984375,
          "cpu_usage_mean": 6.249999999999999,
          "bandwidth_usage_mean": 0.005160713195800781,
          "training_time": 9.338505506515503,
          "train_loss": 1.3330506735897263,
          "train_accuracy": 0.5568458578941795
        },
        "65a5d192b9db43c5ac1cab008a9251c8": {
          "memory_usage_max": 58.5,
          "gpu_memory_max": 26.8984375,
          "cpu_usage_mean": 6.800000000000001,
          "bandwidth_usage_mean": 0.005550265312194824,
          "training_time": 8.042778968811035,
          "train_loss": 1.4307104085552718,
          "train_accuracy": 0.5361208309341365
        }
      }
    },
    {
      "round": 2,
      "aggregated_metrics": {
        "mean_train_loss": 0.7080216612340927,
        "max_train_loss": 0.7422440408932401,
        "mean_train_accuracy": 0.754887875257141,
        "max_train_accuracy": 0.7614950735399114,
        "mean_training_time": 20.341392397880554,
        "max_training_time": 21.80534791946411,
        "mean_cpu_usage_mean": 10.547058823529412,
        "max_cpu_usage_mean": 10.788235294117648,
        "mean_memory_usage_max": 59.4,
        "max_memory_usage_max": 59.4,
        "mean_bandwidth_usage_mean": 0.11198821789076348,
        "max_bandwidth_usage_mean": 0.131471690009622
      },
      "client_metrics": {
        "65a5d192b9db43c5ac1cab008a9251c8": {
          "memory_usage_max": 59.4,
          "gpu_memory_max": 27.283203125,
          "cpu_usage_mean": 10.788235294117648,
          "bandwidth_usage_mean": 0.131471690009622,
          "training_time": 17.08466863632202,
          "train_loss": 0.7076078539416963,
          "train_accuracy": 0.7555476812685477
        },
        "1010b00e8b3146e7aeeba54c7442a467": {
          "memory_usage_max": 59.4,
          "gpu_memory_max": 28.990234375,
          "cpu_usage_mean": 10.385714285714284,
          "bandwidth_usage_mean": 0.10482965196881976,
          "training_time": 21.526959896087646,
          "train_loss": 0.689748872199706,
          "train_accuracy": 0.7604241039554477
        },
        "107f0471e4614155ade41ff1b8b3888a": {
          "memory_usage_max": 59.4,
          "gpu_memory_max": 29.4365234375,
          "cpu_usage_mean": 10.404761904761905,
          "bandwidth_usage_mean": 0.10478646414620536,
          "training_time": 21.80534791946411,
          "train_loss": 0.6924858779017284,
          "train_accuracy": 0.7614950735399114
        },
        "6c5962e51b854d7cb972712fe5bd2d81": {
          "memory_usage_max": 59.4,
          "gpu_memory_max": 24.9091796875,
          "cpu_usage_mean": 10.609523809523811,
          "bandwidth_usage_mean": 0.1068650654384068,
          "training_time": 20.948593139648438,
          "train_loss": 0.7422440408932401,
          "train_accuracy": 0.7420846422646571
        }
      }
    }
  ],
  "client_metrics": {
    "6c5962e51b854d7cb972712fe5bd2d81": [
      {
        "memory_usage_max": 58.6,
        "gpu_memory_max": 24.958984375,
        "cpu_usage_mean": 6.249999999999999,
        "bandwidth_usage_mean": 0.005160713195800781,
        "training_time": 9.338505506515503,
        "train_loss": 1.3330506735897263,
        "train_accuracy": 0.5568458578941795
      },
      {
        "memory_usage_max": 59.4,
        "gpu_memory_max": 24.9091796875,
        "cpu_usage_mean": 10.609523809523811,
        "bandwidth_usage_mean": 0.1068650654384068,
        "training_time": 20.948593139648438,
        "train_loss": 0.7422440408932401,
        "train_accuracy": 0.7420846422646571
      }
    ],
    "65a5d192b9db43c5ac1cab008a9251c8": [
      {
        "memory_usage_max": 58.5,
        "gpu_memory_max": 26.8984375,
        "cpu_usage_mean": 6.800000000000001,
        "bandwidth_usage_mean": 0.005550265312194824,
        "training_time": 8.042778968811035,
        "train_loss": 1.4307104085552718,
        "train_accuracy": 0.5361208309341365
      },
      {
        "memory_usage_max": 59.4,
        "gpu_memory_max": 27.283203125,
        "cpu_usage_mean": 10.788235294117648,
        "bandwidth_usage_mean": 0.131471690009622,
        "training_time": 17.08466863632202,
        "train_loss": 0.7076078539416963,
        "train_accuracy": 0.7555476812685477
      }
    ],
    "1010b00e8b3146e7aeeba54c7442a467": [
      {
        "memory_usage_max": 59.4,
        "gpu_memory_max": 28.990234375,
        "cpu_usage_mean": 10.385714285714284,
        "bandwidth_usage_mean": 0.10482965196881976,
        "training_time": 21.526959896087646,
        "train_loss": 0.689748872199706,
        "train_accuracy": 0.7604241039554477
      }
    ],
    "107f0471e4614155ade41ff1b8b3888a": [
      {
        "memory_usage_max": 59.4,
        "gpu_memory_max": 29.4365234375,
        "cpu_usage_mean": 10.404761904761905,
        "bandwidth_usage_mean": 0.10478646414620536,
        "training_time": 21.80534791946411,
        "train_loss": 0.6924858779017284,
        "train_accuracy": 0.7614950735399114
      }
    ]
  }
}